eFatura/__init__.py
eFatura/arayuz.py
eFatura/konsol.py
eFatura/Assets/logo.png
eFatura/Core/__init__.py
eFatura/GUI/__init__.py
eFatura/Libs/Oturum.py
eFatura/Libs/__init__.py
efatura-1.1.3.data/data/share/appdata/org.KekikAkademi.eFatura.appdata.xml
efatura-1.1.3.data/data/share/applications/org.KekikAkademi.eFatura.desktop
efatura-1.1.3.data/data/share/icons/hicolor/scalable/apps/org.KekikAkademi.eFatura.svg
efatura-1.1.3.dist-info/METADATA
efatura-1.1.3.dist-info/WHEEL
efatura-1.1.3.dist-info/entry_points.txt
efatura-1.1.3.dist-info/top_level.txt
efatura-1.1.3.dist-info/RECORD
