Metadata-Version: 2.2
Name: eFatura
Version: 1.1.3
Summary: Vergi veya TC Kimlik Numarasından E-Fatura Mükellefiyet Sorgusu
Home-page: https://github.com/keyiflerolsun/eFatura
Author: keyiflerolsun
Author-email: keyiflerolsun@gmail.com
License: GPLv3+
Keywords: eFatura,KekikAkademi,keyiflerolsun
Classifier: Development Status :: 5 - Production/Stable
Classifier: License :: OSI Approved :: GNU General Public License v3 or later (GPLv3+)
Classifier: Programming Language :: Python :: 3
Requires-Python: >=3.10
Requires-Dist: setuptools
Requires-Dist: wheel
Requires-Dist: install_freedesktop
Requires-Dist: rich
Requires-Dist: requests
Requires-Dist: urllib3
Requires-Dist: Pillow
Requires-Dist: pytesseract
Dynamic: author
Dynamic: author-email
Dynamic: classifier
Dynamic: description
Dynamic: description-content-type
Dynamic: home-page
Dynamic: keywords
Dynamic: license
Dynamic: requires-dist
Dynamic: requires-python
Dynamic: summary
